poeditor_client/__init__.py
poeditor_client/cmd.py
poeditor_client-0.0.10.data/scripts/poeditor
poeditor_client-0.0.10.dist-info/METADATA
poeditor_client-0.0.10.dist-info/RECORD
poeditor_client-0.0.10.dist-info/WHEEL
poeditor_client-0.0.10.dist-info/top_level.txt
tests/__init__.py
